xpi_blocks/ACS712.py
xpi_blocks/DS1302.py
xpi_blocks/HCSR04-draft.py
xpi_blocks/HDC1080.py
xpi_blocks/L293.py
xpi_blocks/L298.py
xpi_blocks/L298StepperMotorBipolarDraft.py
xpi_blocks/L9110H.py
xpi_blocks/MCP410xx.py
xpi_blocks/ShiftRegister74HC165.py
xpi_blocks/ShiftRegister74HC595.py
xpi_blocks/SimpleRelay.py
xpi_blocks/TB6612FNG.py
xpi_blocks/ULN2003StepperMotorUniPolar.py
xpi_blocks/VNH2SP30.py
xpi_blocks/VoltDiv.py
xpi_blocks/__init__.py
xpi_blocks/ads1115.py
xpi_blocks/at24cXXX.py
xpi_blocks/drv8833.py
xpi_blocks/ds1307.py
xpi_blocks/max17040g.py
xpi_blocks/max44009.py
xpi_blocks/mcp23017.py
xpi_blocks/mcp41xxx.py
xpi_blocks/pca9685.py
xpi_blocks/pcf8574.py
xpi_blocks/smbus_m.py
xpi_blocks/utils.py
xpi_blocks/weather.py
xpi_blocks/ws2812_test.py
xpi_blocks/x9cxxx.py
xpi_blocks-0.0.18.dist-info/LICENSE
xpi_blocks-0.0.18.dist-info/METADATA
xpi_blocks-0.0.18.dist-info/WHEEL
xpi_blocks-0.0.18.dist-info/top_level.txt
xpi_blocks-0.0.18.dist-info/RECORD
